yamdog/_API.py
yamdog/__init__.py
yamdog/dataclass_validate.py
yamdog/py.typed
yamdog-0.6.0.dist-info/LICENSE.txt
yamdog-0.6.0.dist-info/METADATA
yamdog-0.6.0.dist-info/WHEEL
yamdog-0.6.0.dist-info/top_level.txt
yamdog-0.6.0.dist-info/RECORD
