Metadata-Version: 2.1
Name: yamdog
Version: 0.6.0
Summary: Yet Another Markdown Only Generator
Author: Limespy
Project-URL: Homepage, https://github.com/Limespy/yamdog
Project-URL: Changelog, https://github.com/Limespy/yamdog/blob/main/README.md#Changelog
Project-URL: Issue Tracker, https://github.com/Limespy/yamdog/issues
Classifier: Development Status :: 4 - Beta
Classifier: License :: OSI Approved :: MIT License
Classifier: Operating System :: Unix
Classifier: Operating System :: POSIX
Classifier: Operating System :: Microsoft :: Windows
Classifier: Programming Language :: Python :: 3
Classifier: Programming Language :: Python :: 3 :: Only
Classifier: Programming Language :: Python :: 3.10
Classifier: Programming Language :: Python :: 3.11
Classifier: Programming Language :: Python :: 3.12
Classifier: Programming Language :: Python :: 3.13
Requires-Python: >=3.10
License-File: LICENSE.txt
Provides-Extra: build
Requires-Dist: limedev[package] >=0.1.0 ; extra == 'build'
Provides-Extra: dev
Requires-Dist: build >=0.10.0 ; extra == 'dev'
Requires-Dist: colorama >=0.4 ; extra == 'dev'
Requires-Dist: limedev[readme,test] >=0.1.0 ; extra == 'dev'
Requires-Dist: Markdown >=3.4.3 ; extra == 'dev'
Requires-Dist: mypy >=1.2.0 ; extra == 'dev'
Requires-Dist: pre-commit >=3.2.2 ; extra == 'dev'
Requires-Dist: pydantic >=1.10.7 ; extra == 'dev'
Requires-Dist: pylint >=2.17.3 ; extra == 'dev'
Requires-Dist: pympler >=1.0.1 ; extra == 'dev'
Requires-Dist: pytest >=7.2.0 ; extra == 'dev'
Requires-Dist: pytest-cov >=4.0.0 ; extra == 'dev'
Requires-Dist: reorder-python-imports >=3.9.0 ; extra == 'dev'
Requires-Dist: snakemd >=2.1.0 ; extra == 'dev'
Requires-Dist: tomli-w >=1.0.0 ; extra == 'dev'
Requires-Dist: twine >=4.0 ; extra == 'dev'
Requires-Dist: tox >=4.5.1 ; extra == 'dev'
Requires-Dist: wheel >=0.38 ; extra == 'dev'
